{
  "Deps.Superology.api_genity_ex": "elixir-libs",
  "Deps.Superology.aws": "elixir-libs",
  "Deps.Superology.confy": "elixir-libs",
  "Deps.Superology.erlkaf": "elixir-libs",
  "Deps.Superology.ex_shards": "elixir-libs",
  "Deps.Superology.enif_protobuf": "elixir-libs",
  "Deps.Superology.file_assert": "elixir-libs",
  "Deps.Superology.force_assert": "elixir-libs",
  "Deps.Superology.gpb": "elixir-libs",
  "Deps.Superology.http_cure": "elixir-libs",
  "Deps.Superology.kafka_client": "elixir-libs",
  "Deps.Superology.lovely_kafka_client": "elixir-libs",
  "Deps.Superology.metrics_ex": "elixir-libs",
  "Deps.Superology.pretty_kafka_client": "elixir-libs",
  "Deps.Superology.partizan": "elixir-libs",
  "Deps.Superology.protobuf_nif": "elixir-libs",
  "Deps.Superology.ravix": "elixir-libs",
  "Deps.Superology.tracer_x": "elixir-libs",
  "Deps.Superology.trach": "elixir-libs",
  "Deps.Superology.server_sent_events": "elixir-libs",
  "Deps.Superology.formatter": "elixir-libs",
  "Deps.Superology.Freetoplay.freetoplay_models": "elixir-libs-freetoplay",
  "Deps.Superology.Freetoplay.freetoplay_api_models": "elixir-libs-freetoplay",
  "Deps.Superology.Freetoplay.freetoplay_purger_models": "elixir-libs-freetoplay",
  "Deps.Superology.Freetoplay.kafka_freetoplay_models_syncs": "elixir-libs-freetoplay",
  "Deps.Superology.Push.push_models": "elixir-libs-push",
  "Deps.Superology.Push.superology_push_models": "elixir-libs-push",
  "Deps.Superology.Social.kafka_social_models_prefabs": "elixir-libs-social",
  "Deps.Superology.Social.kafka_social_models_syncs": "elixir-libs-social",
  "Deps.Superology.Social.social_api_models": "elixir-libs-social",
  "Deps.Superology.Social.social_models": "elixir-libs-social",
  "Deps.Superology.Social.social_purger_models": "elixir-libs-social",
  "Deps.Superology.Social.social_test_util_api": "elixir-libs-social",
  "Deps.Superology.Stats.api_models": "elixir-libs-stats",
  "Deps.Superology.Stats.axilis_models": "elixir-libs-stats",
  "Deps.Superology.Stats.common_models": "elixir-libs-stats",
  "Deps.Superology.Stats.betradar_livescore_models": "elixir-libs-stats",
  "Deps.Superology.Stats.betradar_kafka_syncs": "elixir-libs-stats",
  "Deps.Superology.Stats.joiner_kafka_syncs": "elixir-libs-stats",
  "Deps.Superology.Stats.opta_kafka_syncs": "elixir-libs-stats",
  "Deps.Superology.Stats.opta_models": "elixir-libs-stats",
  "Deps.Superology.Stats.providerids_kafka_syncs": "elixir-libs-stats",
  "Deps.Superology.Stats.purger_models": "elixir-libs-stats",
  "Deps.Superology.Stats.superology_api_models": "elixir-libs-stats",
  "Deps.Superology.Stats.superology_consolidated_models": "elixir-libs-stats",
  "Deps.Superology.Stats.superology_kafka_syncs": "elixir-libs-stats",
  "Deps.Superology.Stats.sync_behavior": "elixir-libs-stats",
  "Deps.Superology.Superfeeds.sf_betradar_models": "elixir-libs-superfeeds",
  "Deps.Superology.Superfeeds.sf_common_models": "elixir-libs-superfeeds",
  "Deps.Superology.Superfeeds.sf_sportradar_models": "elixir-libs-superfeeds",
  "Deps.Superology.Superfeeds.sf_sportradar_kafka_syncs": "elixir-libs-superfeeds",
  "Deps.Superology.Superfeeds.sf_entity_pairing_models": "elixir-libs-superfeeds",
  "Deps.Superology.Superfeeds.sf_universal_gamestate_models": "elixir-libs-superfeeds",
  "Deps.Superology.Superfeeds.sf_entity_pair_domain_syncs": "elixir-libs-superfeeds"
}
